hydroqc2mqtt/__init__.py
hydroqc2mqtt/__main__.py
hydroqc2mqtt/__version__.py
hydroqc2mqtt/contract_device.py
hydroqc2mqtt/daemon.py
hydroqc2mqtt/error.py
hydroqc2mqtt/hourly_consump_handler.py
hydroqc2mqtt/sensors.py
hydroqc2mqtt-2.0.0.dist-info/LICENSE
hydroqc2mqtt-2.0.0.dist-info/METADATA
hydroqc2mqtt-2.0.0.dist-info/WHEEL
hydroqc2mqtt-2.0.0.dist-info/entry_points.txt
hydroqc2mqtt-2.0.0.dist-info/top_level.txt
hydroqc2mqtt-2.0.0.dist-info/RECORD
