Metadata-Version: 2.1
Name: hydroqc2mqtt
Version: 2.0.0
Summary: Daemon managing hydroqc sensors through MQTT
Home-page: https://hydroqc.ca
Author-email: Hydroqc Team <info@hydroqc.ca>
License: AGPL-3.0-or-later
Project-URL: Source Code, https://gitlab.com/hydroqc/hydroqc2mqtt
Project-URL: Bug Reports, https://gitlab.com/hydroqc/hydroqc2mqtt/-/issues
Project-URL: Home-page, https://hydroqc.ca
Keywords: hydro-quebec,mqtt,homeassistant,hydroqc
Platform: any
Classifier: Programming Language :: Python :: 3
Classifier: License :: OSI Approved :: MIT License
Classifier: Operating System :: OS Independent
Requires-Python: >=3.12.0
License-File: LICENSE
Requires-Dist: mqtt-hass-base ==4.4.0
Requires-Dist: Hydro-Quebec-API-Wrapper ==4.0.0
Requires-Dist: python-dateutil ==2.9.0.post0
Requires-Dist: packaging ==24.1
Requires-Dist: pytz ==2024.2
Requires-Dist: homeassistant
Requires-Dist: charset-normalizer ==3.3.2
